{"name":"Successful booking","id":"reserve-a-flight;successful-booking","testSteps":[{"number":1,"description":"Given that a web user wants to reserve a flight at avianca","duration":9113,"startTime":"2021-07-18T10:16:49.615517200-05:00[America/Bogota]","screenshots":[{"screenshot":"a5ba9e7a2566c515e44afa66f3586ec586026a1ce22d8b8805c4d7fa46af6760.png","timeStamp":1626621418729}],"result":"SUCCESS","precondition":false,"level":0,"children":[{"number":2,"description":"Open browser","duration":8764,"startTime":"2021-07-18T10:16:49.959182300-05:00[America/Bogota]","screenshots":[{"screenshot":"a5ba9e7a2566c515e44afa66f3586ec586026a1ce22d8b8805c4d7fa46af6760.png","timeStamp":1626621418723}],"result":"SUCCESS","precondition":false,"level":1}]},{"number":3,"description":"When he fills all the requested fields","duration":48820,"startTime":"2021-07-18T10:16:58.731394800-05:00[America/Bogota]","screenshots":[{"screenshot":"df5e6505be6c1a751898b3e22025470b4796ece6b4bce7fb821b500f36bd57a1.png","timeStamp":1626621467552}],"result":"SUCCESS","precondition":false,"level":0,"children":[{"number":4,"description":"Fill flight data","duration":48812,"startTime":"2021-07-18T10:16:58.737380400-05:00[America/Bogota]","screenshots":[{"screenshot":"df5e6505be6c1a751898b3e22025470b4796ece6b4bce7fb821b500f36bd57a1.png","timeStamp":1626621467550}],"result":"SUCCESS","precondition":false,"level":1}]},{"number":5,"description":"Then he should see his flight reservation","duration":2,"startTime":"2021-07-18T10:17:47.553251-05:00[America/Bogota]","screenshots":[{"screenshot":"df5e6505be6c1a751898b3e22025470b4796ece6b4bce7fb821b500f36bd57a1.png","timeStamp":1626621467556}],"result":"SUCCESS","precondition":false,"level":0}],"userStory":{"id":"reserve-a-flight","storyName":"Reserve a flight","path":"src/test/resources/features/avianca.feature","narrative":"  As a web user\n  I want to Reserve a flight\n  at Avianca.com","type":"feature"},"featureTag":{"name":"Features/Reserve a flight","type":"feature","displayName":"Features/Reserve a flight"},"title":"Successful booking","tags":[{"name":"smokeTest","type":"tag","displayName":"smokeTest"},{"name":"Reserve a flight","type":"feature","displayName":"Reserve a flight"}],"startTime":"2021-07-18T10:16:49.521784100-05:00[America/Bogota]","duration":58036,"projectKey":"","sessionId":"712bb69fdd6a6aaec8e83189d9ad740e","driver":"chrome","isManualTestingUpToDate":false,"manual":false,"testSource":"Cucumber","result":"SUCCESS"}